qiskit_dynamics/VERSION.txt
qiskit_dynamics/__init__.py
qiskit_dynamics/version.py
qiskit_dynamics/arraylias/__init__.py
qiskit_dynamics/arraylias/alias.py
qiskit_dynamics/arraylias/register_functions/__init__.py
qiskit_dynamics/arraylias/register_functions/asarray.py
qiskit_dynamics/arraylias/register_functions/conjugate.py
qiskit_dynamics/arraylias/register_functions/linear_combo.py
qiskit_dynamics/arraylias/register_functions/matmul.py
qiskit_dynamics/arraylias/register_functions/multiply.py
qiskit_dynamics/arraylias/register_functions/rmatmul.py
qiskit_dynamics/arraylias/register_functions/transpose.py
qiskit_dynamics/backend/__init__.py
qiskit_dynamics/backend/backend_utils.py
qiskit_dynamics/backend/dynamics_backend.py
qiskit_dynamics/backend/dynamics_job.py
qiskit_dynamics/models/__init__.py
qiskit_dynamics/models/generator_model.py
qiskit_dynamics/models/hamiltonian_model.py
qiskit_dynamics/models/lindblad_model.py
qiskit_dynamics/models/model_utils.py
qiskit_dynamics/models/operator_collections.py
qiskit_dynamics/models/rotating_frame.py
qiskit_dynamics/models/rotating_wave_approximation.py
qiskit_dynamics/perturbation/__init__.py
qiskit_dynamics/perturbation/array_polynomial.py
qiskit_dynamics/perturbation/custom_binary_op.py
qiskit_dynamics/perturbation/dyson_magnus.py
qiskit_dynamics/perturbation/multiset_utils.py
qiskit_dynamics/perturbation/perturbation_data.py
qiskit_dynamics/perturbation/perturbation_utils.py
qiskit_dynamics/perturbation/solve_lmde_perturbation.py
qiskit_dynamics/pulse/__init__.py
qiskit_dynamics/pulse/pulse_to_signals.py
qiskit_dynamics/signals/__init__.py
qiskit_dynamics/signals/signals.py
qiskit_dynamics/signals/transfer_functions.py
qiskit_dynamics/solvers/__init__.py
qiskit_dynamics/solvers/diffrax_solver.py
qiskit_dynamics/solvers/fixed_step_solvers.py
qiskit_dynamics/solvers/jax_odeint.py
qiskit_dynamics/solvers/lanczos.py
qiskit_dynamics/solvers/scipy_solve_ivp.py
qiskit_dynamics/solvers/solver_classes.py
qiskit_dynamics-0.6.0.dist-info/licenses/LICENSE.txt
qiskit_dynamics-0.6.0.dist-info/METADATA
qiskit_dynamics-0.6.0.dist-info/WHEEL
qiskit_dynamics-0.6.0.dist-info/top_level.txt
qiskit_dynamics-0.6.0.dist-info/RECORD
