Metadata-Version: 2.4
Name: qiskit-dynamics
Version: 0.6.0
Summary: Qiskit ODE solver
Home-page: https://github.com/Qiskit-Community/qiskit-dynamics
Author: Qiskit Development Team
Author-email: qiskit@us.ibm.com
License: Apache 2.0
Project-URL: Bug Tracker, https://github.com/Qiskit-Community/qiskit-dynamics/issues
Project-URL: Source Code, https://github.com/Qiskit-Community/qiskit-dynamics
Project-URL: Documentation, https://qiskit-community.github.io/qiskit-dynamics/
Keywords: qiskit sdk quantum
Classifier: Environment :: Console
Classifier: License :: OSI Approved :: Apache Software License
Classifier: Intended Audience :: Developers
Classifier: Intended Audience :: Science/Research
Classifier: Operating System :: Microsoft :: Windows
Classifier: Operating System :: MacOS
Classifier: Operating System :: POSIX :: Linux
Classifier: Programming Language :: Python :: 3 :: Only
Classifier: Programming Language :: Python :: 3.10
Classifier: Programming Language :: Python :: 3.11
Classifier: Programming Language :: Python :: 3.12
Classifier: Programming Language :: Python :: 3.13
Classifier: Topic :: Scientific/Engineering
Requires-Python: >=3.10
License-File: LICENSE.txt
Requires-Dist: numpy>=1.17
Requires-Dist: scipy>=1.4
Requires-Dist: matplotlib>=3.0
Requires-Dist: qiskit<=1.3
Requires-Dist: multiset>=3.0.1
Requires-Dist: sympy>=1.12
Requires-Dist: arraylias
Provides-Extra: jax
Requires-Dist: jax; extra == "jax"
Requires-Dist: jaxlib; extra == "jax"
Dynamic: author
Dynamic: author-email
Dynamic: classifier
Dynamic: description
Dynamic: description-content-type
Dynamic: home-page
Dynamic: keywords
Dynamic: license
Dynamic: license-file
Dynamic: project-url
Dynamic: provides-extra
Dynamic: requires-dist
Dynamic: requires-python
Dynamic: summary
